dv_processing.pypy310-pp73-x86_64-linux-gnu.so
dv_processing.libs/libatomic-758ea376.so.1.2.0
dv_processing.libs/libblkid-a9167753.so.1.1.0
dv_processing.libs/libmount-ec61bd71.so.1.1.0
dv_processing.libs/libpcre2-8-516f4c9d.so.0.7.1
dv_processing.libs/libselinux-d0805dcb.so.1
dv_processing.libs/libudev-9765ffbd.so.1.6.11
dv_processing.libs/libuuid-95b83d40.so.1.3.0
dv_processing-2.0.2.dist-info/METADATA
dv_processing-2.0.2.dist-info/WHEEL
dv_processing-2.0.2.dist-info/top_level.txt
dv_processing-2.0.2.dist-info/RECORD
dv_processing-2.0.2.dist-info/licenses/LICENSE
