Metadata-Version: 2.4
Name: dv_processing
Version: 2.0.2
Summary: Generic algorithms for event cameras.
Author: iniVation AG
Author-email: support@inivation.com
Requires-Python: >=3.8
License-File: LICENSE
Requires-Dist: numpy
Dynamic: author
Dynamic: author-email
Dynamic: license-file
Dynamic: requires-dist
Dynamic: requires-python
Dynamic: summary
